encodingscorepy/__init__.py
encodingscorepy/base64_eval.py
encodingscorepy/decimal_eval.py
encodingscorepy/evaluator.py
encodingscorepy/evaluator_factory.py
encodingscorepy/hexadecimal_eval.py
encodingscorepy/octal_eval.py
encodingscorepy/scorer.py
encodingscorepy/validation.py
encodingscorepy-1.1.0.dist-info/licenses/LICENSE
encodingscorepy-1.1.0.dist-info/METADATA
encodingscorepy-1.1.0.dist-info/WHEEL
encodingscorepy-1.1.0.dist-info/top_level.txt
encodingscorepy-1.1.0.dist-info/RECORD
