Metadata-Version: 2.4
Name: encodingscorepy
Version: 1.1.0
Summary: A library for scoring encoded text against a provided regex.
Author-email: Rebase <rebased.again@gmail.com>
License-Expression: MIT
Classifier: Programming Language :: Python :: 3
Classifier: Operating System :: OS Independent
Requires-Python: >=3.9
License-File: LICENSE
Dynamic: license-file
